weditor/__init__.py
weditor/__main__.py
weditor/page.xml
weditor/static/favicon.ico
weditor/static/loading.svg
weditor/static/running.svg
weditor/static/style.css
weditor/static/ace/ace.js
weditor/static/ace/ext-language_tools.js
weditor/static/ace/keybinding-vim.js
weditor/static/ace/mode-python.js
weditor/static/ace/theme-monokai.js
weditor/static/cdn_libraries/cdn.jsdelivr.net/bootstrap/3.3.7/css/bootstrap.min.css
weditor/static/cdn_libraries/cdn.jsdelivr.net/bootstrap/3.3.7/css/bootstrap.min.css.map
weditor/static/cdn_libraries/cdn.jsdelivr.net/bootstrap/3.3.7/fonts/glyphicons-halflings-regular.woff2
weditor/static/cdn_libraries/cdn.jsdelivr.net/bootstrap/3.3.7/js/bootstrap.min.js
weditor/static/cdn_libraries/cdn.jsdelivr.net/bootstrap.select/1.12.2/css/bootstrap-select.min.css
weditor/static/cdn_libraries/cdn.jsdelivr.net/bootstrap.select/1.12.2/js/bootstrap-select.js.map
weditor/static/cdn_libraries/cdn.jsdelivr.net/bootstrap.select/1.12.2/js/bootstrap-select.min.js
weditor/static/cdn_libraries/cdn.jsdelivr.net/npm/vue-resource@1.5.1
weditor/static/cdn_libraries/cdn.jsdelivr.net/npm/ace-builds@1.4.12/src-noconflict/ace.min.js
weditor/static/cdn_libraries/cdn.jsdelivr.net/npm/ace-builds@1.4.12/src-noconflict/ext-language_tools.min.js
weditor/static/cdn_libraries/cdn.jsdelivr.net/npm/ace-builds@1.4.12/src-noconflict/ext-searchbox.min.js
weditor/static/cdn_libraries/cdn.jsdelivr.net/npm/ace-builds@1.4.12/src-noconflict/mode-python.min.js
weditor/static/cdn_libraries/cdn.jsdelivr.net/npm/ace-builds@1.4.12/src-noconflict/theme-monokai.js
weditor/static/cdn_libraries/cdn.jsdelivr.net/npm/jquery@3.3.1/dist/jquery.min.js
weditor/static/cdn_libraries/cdn.jsdelivr.net/npm/jstree@3.3.8/dist/jstree.min.js
weditor/static/cdn_libraries/cdn.jsdelivr.net/npm/jstree@3.3.8/dist/themes/default/32px.png
weditor/static/cdn_libraries/cdn.jsdelivr.net/npm/jstree@3.3.8/dist/themes/default/style.min.css
weditor-0.6.4.dist-info/AUTHORS
weditor-0.6.4.dist-info/LICENSE
weditor-0.6.4.dist-info/METADATA
weditor-0.6.4.dist-info/WHEEL
weditor-0.6.4.dist-info/entry_points.txt
weditor-0.6.4.dist-info/pbr.json
weditor-0.6.4.dist-info/top_level.txt
weditor-0.6.4.dist-info/RECORD
