Metadata-Version: 2.1
Name: weditor
Version: 0.6.4
Summary: tool for writing atx script
Home-page: https://github.com/openatx/weditor
Author: codeskyblue
Author-email: codeskyblue@gmail.com
License: MIT
Platform: UNKNOWN
Classifier: Environment :: Console
Classifier: Intended Audience :: Developers
Classifier: Operating System :: OS Independent
Classifier: Programming Language :: Python
Requires-Python: >=3.6
